leapocr/__init__.py
leapocr/client.py
leapocr/config.py
leapocr/errors.py
leapocr/models.py
leapocr/ocr.py
leapocr/py.typed
leapocr/_internal/__init__.py
leapocr/_internal/polling.py
leapocr/_internal/retry.py
leapocr/_internal/upload.py
leapocr/_internal/utils.py
leapocr/_internal/validation.py
leapocr/generated/.openapi-generator-ignore
leapocr/generated/.openapi-generator/FILES
leapocr/generated/.openapi-generator/VERSION
leapocr/generated/leapocr/__init__.py
leapocr/generated/leapocr/generated_README.md
leapocr/generated/leapocr/generated/__init__.py
leapocr/generated/leapocr/generated/api_client.py
leapocr/generated/leapocr/generated/api_response.py
leapocr/generated/leapocr/generated/configuration.py
leapocr/generated/leapocr/generated/exceptions.py
leapocr/generated/leapocr/generated/rest.py
leapocr/generated/leapocr/generated/api/__init__.py
leapocr/generated/leapocr/generated/api/analytics_api.py
leapocr/generated/leapocr/generated/api/authentication_api.py
leapocr/generated/leapocr/generated/api/credits_api.py
leapocr/generated/leapocr/generated/api/health_api.py
leapocr/generated/leapocr/generated/api/jobs_api.py
leapocr/generated/leapocr/generated/api/models_api.py
leapocr/generated/leapocr/generated/api/ocr_api.py
leapocr/generated/leapocr/generated/api/sdk_api.py
leapocr/generated/leapocr/generated/api/templates_api.py
leapocr/generated/leapocr/generated/api/upload_api.py
leapocr/generated/leapocr/generated/api/webhooks_api.py
leapocr/generated/leapocr/generated/models/__init__.py
leapocr/generated/leapocr/generated/models/analytics_credits_overview.py
leapocr/generated/leapocr/generated/models/analytics_credits_timeseries_point.py
leapocr/generated/leapocr/generated/models/analytics_credits_usage_response.py
leapocr/generated/leapocr/generated/models/analytics_job_overview.py
leapocr/generated/leapocr/generated/models/analytics_job_timeseries_point.py
leapocr/generated/leapocr/generated/models/analytics_jobs_timeseries_get200_response.py
leapocr-0.0.3.dist-info/METADATA
leapocr-0.0.3.dist-info/WHEEL
leapocr-0.0.3.dist-info/licenses/LICENSE
leapocr-0.0.3.dist-info/RECORD
