Metadata-Version: 2.4
Name: leapocr
Version: 0.0.3
Summary: Official Python SDK for LeapOCR - Transform documents into structured data using AI-powered OCR
Project-URL: Homepage, https://leapocr.com
Project-URL: Documentation, https://docs.leapocr.com
Project-URL: Repository, https://github.com/leapocr/leapocr-python
Project-URL: Issues, https://github.com/leapocr/leapocr-python/issues
Project-URL: Logo, https://raw.githubusercontent.com/LeapOCR/leapocr-python/refs/heads/main/logo/web-app-manifest-512x512.png
Author-email: LeapOCR <support@leapocr.com>
Maintainer-email: LeapOCR <support@leapocr.com>
License: Apache-2.0
License-File: LICENSE
Keywords: ai,api-client,artificial-intelligence,async,asyncio,data-extraction,document-extraction,document-processing,ocr,optical-character-recognition,pdf,sdk,structured-data,text-extraction
Classifier: Development Status :: 4 - Beta
Classifier: Framework :: AsyncIO
Classifier: Intended Audience :: Developers
Classifier: Intended Audience :: Information Technology
Classifier: Intended Audience :: Science/Research
Classifier: License :: OSI Approved :: Apache Software License
Classifier: Operating System :: OS Independent
Classifier: Programming Language :: Python
Classifier: Programming Language :: Python :: 3
Classifier: Programming Language :: Python :: 3 :: Only
Classifier: Programming Language :: Python :: 3.9
Classifier: Programming Language :: Python :: 3.10
Classifier: Programming Language :: Python :: 3.11
Classifier: Programming Language :: Python :: 3.12
Classifier: Topic :: Internet :: WWW/HTTP :: Dynamic Content
Classifier: Topic :: Office/Business
Classifier: Topic :: Scientific/Engineering
Classifier: Topic :: Scientific/Engineering :: Artificial Intelligence
Classifier: Topic :: Scientific/Engineering :: Image Recognition
Classifier: Topic :: Software Development :: Libraries
Classifier: Topic :: Software Development :: Libraries :: Python Modules
Classifier: Topic :: Text Processing
Classifier: Topic :: Text Processing :: Markup
Classifier: Typing :: Typed
Requires-Python: >=3.9
Requires-Dist: httpx>=0.28.0
Requires-Dist: pydantic<2.0,>=1.10.24
Requires-Dist: typing-extensions>=4.12.0
Provides-Extra: dev
Requires-Dist: mypy>=1.18.0; extra == 'dev'
Requires-Dist: pre-commit<4.4.0,>=4.3.0; extra == 'dev'
Requires-Dist: pytest-asyncio<1.3.0,>=1.2.0; extra == 'dev'
Requires-Dist: pytest-cov>=7.0.0; extra == 'dev'
Requires-Dist: pytest<9.0.0,>=8.4.0; extra == 'dev'
Requires-Dist: ruff>=0.14.0; extra == 'dev'
